pic_scanner/__init__.py
pic_scanner/api/__init__.py
pic_scanner/cli/__init__.py
pic_scanner/cli/arguments/__init__.py
pic_scanner/cli/core_subcommands/__init__.py
pic_scanner/cli/subcommands/__init__.py
pic_scanner/cli/subcommands/community/__init__.py
pic_scanner/cli/subcommands/core/__init__.py
pic_scanner/cli/subcommands/core/version_info.py
pic_scanner/cli/subcommands/registry.py
pic_scanner/common/__about__.py
pic_scanner/common/__init__.py
pic_scanner/common/constants/__init__.py
pic_scanner/common/constants/defaults/__init__.py
pic_scanner/common/constants/defaults/dirs.py
pic_scanner/common/constants/defaults/files.py
pic_scanner/common/meta/__init__.py
pic_scanner/common/meta/constants.py
pic_scanner/common/meta/version.py
pic_scanner/core/__init__.py
pic_scanner/core/cli.py
pic_scanner/download_scanner/__init__.py
pic_scanner/gui/__init__.py
pic_scanner/gui/models/__init__.py
pic_scanner/gui/models/element_bases/__init__.py
pic_scanner/gui/models/element_bases/blueprint.py
pic_scanner/gui/models/element_bases/column.py
pic_scanner/gui/models/element_bases/metas.py
pic_scanner/gui/models/windows/__init__.py
pic_scanner/gui/models/windows/main/__init__.py
pic_scanner/gui/models/windows/main/blueprint/__init__.py
pic_scanner/gui/models/windows/main/blueprint/columns/__init__.py
pic_scanner/gui/models/windows/template.py
pic_scanner/helpers/__init__.py
pic_scanner/helpers/filesystem/__init__.py
pic_scanner/helpers/filesystem/classes.py
pic_scanner/helpers/filesystem/units.py
pic_scanner/helpers/images.py
pic_scanner/helpers/locks.py
pic_scanner/helpers/properties.py
pic_scanner/log_engine/__init__.py
pic_scanner/models/__init__.py
pic_scanner/models/concern.py
pic_scanner/models/image.py
pic_scanner-1.0.0.dev1.dist-info/LICENSE.md
pic_scanner-1.0.0.dev1.dist-info/METADATA
pic_scanner-1.0.0.dev1.dist-info/WHEEL
pic_scanner-1.0.0.dev1.dist-info/RECORD
